quant_tick/__init__.py
quant_tick/apps.py
quant_tick/constants.py
quant_tick/controllers/__init__.py
quant_tick/controllers/base.py
quant_tick/controllers/constants.py
quant_tick/controllers/iterators.py
quant_tick/controllers/rest.py
quant_tick/controllers/s3.py
quant_tick/exchanges/__init__.py
quant_tick/exchanges/alpaca/__init__.py
quant_tick/exchanges/api.py
quant_tick/exchanges/binance/__init__.py
quant_tick/exchanges/binance/api.py
quant_tick/exchanges/binance/base.py
quant_tick/exchanges/binance/candles.py
quant_tick/exchanges/binance/constants.py
quant_tick/exchanges/binance/controllers.py
quant_tick/exchanges/bitfinex/__init__.py
quant_tick/exchanges/bitfinex/api.py
quant_tick/exchanges/bitfinex/base.py
quant_tick/exchanges/bitfinex/candles.py
quant_tick/exchanges/bitfinex/constants.py
quant_tick/exchanges/bitfinex/controllers.py
quant_tick/exchanges/bitfinex/trades.py
quant_tick/exchanges/bitflyer/__init__.py
quant_tick/exchanges/bitflyer/api.py
quant_tick/exchanges/bitflyer/base.py
quant_tick/exchanges/bitflyer/constants.py
quant_tick/exchanges/bitflyer/controllers.py
quant_tick/exchanges/bitmex/__init__.py
quant_tick/exchanges/bitmex/api.py
quant_tick/exchanges/bitmex/base.py
quant_tick/exchanges/bitmex/candles.py
quant_tick/exchanges/bitmex/constants.py
quant_tick/exchanges/bitmex/controllers.py
quant_tick/exchanges/bitmex/funding.py
quant_tick/exchanges/bitmex/lib.py
quant_tick/exchanges/bitmex/trades.py
quant_tick/exchanges/bybit/__init__.py
quant_tick/exchanges/bybit/api.py
quant_tick/exchanges/bybit/base.py
quant_tick/exchanges/bybit/candles.py
quant_tick/exchanges/bybit/constants.py
quant_tick/exchanges/bybit/controllers.py
quant_tick/exchanges/coinbase/__init__.py
quant_tick/exchanges/coinbase/api.py
quant_tick/exchanges/coinbase/base.py
quant_tick/exchanges/coinbase/candles.py
quant_tick/exchanges/coinbase/constants.py
quant_tick/exchanges/coinbase/controllers.py
quant_tick/exchanges/coinbase/trades.py
quant_tick/exchanges/kucoin/__init__.py
django_quant_tick-0.1.3.dist-info/LICENSE
django_quant_tick-0.1.3.dist-info/METADATA
django_quant_tick-0.1.3.dist-info/WHEEL
django_quant_tick-0.1.3.dist-info/RECORD
