Metadata-Version: 2.1
Name: django-quant-tick
Version: 0.1.3
Summary: Django Quant Tick downloads and aggregate candlesticks from tick data
Home-page: https://github.com/globophobe/django-quant-tick
License: MIT
Keywords: django,cryptocurrency,candlesticks,quant,trading,tick,data
Author: Alex
Author-email: globophobe@gmail.com
Requires-Python: >=3.8, !=2.7.*, !=3.0.*, !=3.1.*, !=3.2.*, !=3.3.*, !=3.4.*, !=3.5.*, !=3.6.*, !=3.7.*, !=3.11.*
Classifier: Development Status :: 4 - Beta
Classifier: License :: OSI Approved :: MIT License
Classifier: Operating System :: OS Independent
Classifier: Programming Language :: Python :: 3
Classifier: Programming Language :: Python :: 3.8
Classifier: Programming Language :: Python :: 3.9
Classifier: Programming Language :: Python :: 3.10
Requires-Dist: django-polymorphic
Requires-Dist: djangorestframework
Requires-Dist: httpx
Requires-Dist: pandas
Requires-Dist: pyarrow
Requires-Dist: randomname
Project-URL: Repository, https://github.com/globophobe/django-quant-tick
